{"resourceType":"MedicationDispense","id":"nl-core-AdministrationAgreement-01","meta":{"profile":["http://nictiz.nl/fhir/StructureDefinition/nl-core-AdministrationAgreement"]},"extension":[{"url":"http://nictiz.nl/fhir/StructureDefinition/ext-AdministrationAgreement.AdministrationAgreementDateTime","valueDateTime":"2012-05-02T12:14:09+02:00"},{"url":"http://nictiz.nl/fhir/StructureDefinition/ext-RenderedDosageInstruction","valueString":"Vanaf 2 mei gedurende 4 weken zo nodig bij pijn 500 mg (=1 st), max. 4x per dag"},{"url":"http://nictiz.nl/fhir/StructureDefinition/ext-TimeInterval-Period","valuePeriod":{"start":"2012-05-02","end":"2012-05-30"}}],"modifierExtension":[{"url":"http://nictiz.nl/fhir/StructureDefinition/ext-InstructionsForUse.RepeatPeriodCyclicalSchedule","valueDuration":{"value":1,"unit":"d","system":"http://unitsofmeasure.org","code":"d"}}],"status":"completed","category":{"coding":[{"system":"http://snomed.info/sct","code":"422037009","display":"toedieningsafspraak"}]},"medicationReference":{"reference":"Medication/nl-core-AdministrationAgreement-01-Medication-01","type":"Medication","display":"PARACETAMOL 500MG TABLET"},"subject":{"reference":"Patient/nl-core-Patient-01","type":"Patient","display":"Patient, Johanna Petronella Maria J.P.M. Jo van Putten van der Giessen"},"performer":[{"actor":{"reference":"Organization/nl-core-AdministrationAgreement-01-Organization-01","type":"Organization","display":"Healthcare provider (organization), Apotheek De Gulle Gaper"}}],"authorizingPrescription":[{"reference":"MedicationRequest/nl-core-AdministrationAgreement-01-MedicationRequest-01","type":"MedicationRequest"}],"dosageInstruction":[{"timing":{"repeat":{"boundsDuration":{"value":4,"unit":"wk","system":"http://unitsofmeasure.org","code":"wk"},"frequencyMax":4,"period":1,"periodUnit":"d"}},"asNeededCodeableConcept":{"coding":[{"system":"https://referentiemodel.nhg.org/tabellen/nhg-tabel-25-gebruiksvoorschrift#aanvullend-numeriek","code":"1028","display":"Bij pijn"}]},"route":{"coding":[{"system":"urn:oid:2.16.840.1.113883.2.4.4.9","code":"oraal"}]},"doseAndRate":[{"doseQuantity":{"value":1,"unit":"stuk","system":"http://unitsofmeasure.org","code":"{stuk}"}}]}]}