{"resourceType":"MedicationDispense","id":"nl-core-MedicationDispense-01","meta":{"profile":["http://nictiz.nl/fhir/StructureDefinition/zib-MedicationDispense"]},"extension":[{"url":"http://nictiz.nl/fhir/StructureDefinition/ext-MedicationDispense.RequestDate","valueDateTime":"2012-05-02T10:19:08+02:00"}],"status":"completed","category":{"coding":[{"system":"http://snomed.info/sct","code":"373784005","display":"verstrekken van medicatie"}]},"medicationReference":{"reference":"Medication/nl-core-MedicationDispense-01-Medication-01","type":"Medication","display":"PARACETAMOL 500MG TABLET"},"subject":{"reference":"Patient/nl-core-Patient-01","type":"Patient","display":"Patient, Johanna Petronella Maria J.P.M. Jo van Putten van der Giessen"},"performer":[{"actor":{"reference":"Organization/nl-core-AdministrationAgreement-01-Organization-01","type":"Organization","display":"Healthcare provider (organization), Apotheek De Gulle Gaper"}}],"quantity":{"value":100,"unit":"tabletten","system":"http://unitsofmeasure.org","code":"{tabletten}"},"daysSupply":{"value":4,"unit":"wk","system":"http://unitsofmeasure.org","code":"wk"},"whenHandedOver":"2012-05-03T12:04:51+02:00"}